{
    "os": "Fedora 12",
    "client": "Pidgin",
    "clientversion": "2.7",
	"author": 
		{
			"name": "Michael Schönitzer",
			"email": "michael (ät) schoenitzer.de",
			"website": "http://www.schoenitzer.de",
			"jabber": "Schoenitzer@jabber.piratenpartei.de"
		},
    "tutorial": [
        {
            "image":    "fedora-pidgin1.png",
            "text":     "Um Pidgin zu installieren muss zunächst das Softwarecenter gestartet werden."
        },
		{
            "image":    "fedora-pidgin2.png",
            "text":     "Suche nach Pidgin und wähle dann die aktuelle Version von Pidgin und fals gewünscht die zusätzlichen Plugins dafür aus. Klicke auf ok und gebe wenn nötig ihr root-Passwort ein."
        },
        {
            "image":    "fedora-pidgin3.png",
            "text":     "Nun kannst du Pidgin über Anwendungen->Internet->Pidgin... starten."
        },
        {
            "image":    "fedora-pidgin4.png",
            "text":     "Bei ersten Start wirst du mit diesem Fenster begrüßt. Klicke auf \"Add...\""
        },
        {
            "image":    "fedora-pidgin5.png",
            "text":     "Wähle als Protokoll \"XMPP\" aus. Als Benutzer dient der Teil deiner Jabber-Adresse, der vor dem @ steht. Der Teil nach dem @, kommt in das Feld \"Domain\". Das Feld Ressource kann leer bleiben. Dein Passwort gehört in das entsprechende Feld. Alles ander ist optional. Mit einem Klick auf \"Hinzufügen\" wird das Fenster geschlossen."
        },
        {
            "image":    "fedora-pidgin6.png",
            "text":     "Hier kannst du Akounts aktivieren/deaktivieren und weiter Account hinzufügen. Nach einem Klick auf \"Schließen\" kannst du Pidgin verwenden."
        }


    ],
    "links": [
        {
            "linktext": "offizielle Seite von Pidgin",
            "url":      "http://pidgin.im"
        }
    ]
}

